setup.py
Another_One_Messenger_Server.egg-info/PKG-INFO
Another_One_Messenger_Server.egg-info/SOURCES.txt
Another_One_Messenger_Server.egg-info/dependency_links.txt
Another_One_Messenger_Server.egg-info/requires.txt
Another_One_Messenger_Server.egg-info/top_level.txt
src/__init__.py
src/server.py
src/common/__init__.py
src/common/decos.py
src/common/descryptors.py
src/common/errors.py
src/common/metaclasses.py
src/common/utils.py
src/common/variables.py
src/logs/__init__.py
src/logs/config_client_log.py
src/logs/config_server_log.py
src/server/__init__.py
src/server/add_user.py
src/server/config_window.py
src/server/core.py
src/server/database.py
src/server/main_window.py
src/server/remove_user.py
src/server/stat_window.py