Metadata-Version: 1.0
Name: Another-One-Messenger-Server
Version: 0.9
Summary: Messenger_server
Home-page: UNKNOWN
Author: Mihail Pendyurin
Author-email: mihail.pendyurin@rt.ru
License: UNKNOWN
Platform: UNKNOWN
